mao_45m/__init__.py
mao_45m/cosmos.py
mao_45m/utils.py
mao_45m/epl/__init__.py
mao_45m/epl/convert.py
mao_45m/subref/__init__.py
mao_45m/subref/control.py
mao_45m/subref/convert.py
mao_45m/subref/epl.py
mao_45m/vdif/__init__.py
mao_45m/vdif/convert.py
mao_45m/vdif/receive.py
mao_45m/vdif/send.py
mao_45m-0.8.0.dist-info/METADATA
mao_45m-0.8.0.dist-info/WHEEL
mao_45m-0.8.0.dist-info/entry_points.txt
mao_45m-0.8.0.dist-info/licenses/LICENSE
mao_45m-0.8.0.dist-info/RECORD
