Metadata-Version: 2.4
Name: mao-45m
Version: 0.8.0
Summary: MAO controller for the Nobeyama 45m telescope
Project-URL: repository, https://github.com/mao-wfs/mao-45m
Author-email: Akio Taniguchi <taniguchi.akio@gmail.com>
License: MIT License
License-File: LICENSE
Classifier: License :: OSI Approved :: MIT License
Classifier: Programming Language :: Python :: 3
Classifier: Programming Language :: Python :: 3.10
Classifier: Programming Language :: Python :: 3.11
Classifier: Programming Language :: Python :: 3.12
Classifier: Programming Language :: Python :: 3.13
Requires-Python: <3.14,>=3.10
Requires-Dist: dateparser<2,>=1
Requires-Dist: decode<2026.0,>=2025.6
Requires-Dist: fire<1.0,>=0.7
Requires-Dist: matplotlib<4,>=3
Requires-Dist: ndtools<2,>=1
Requires-Dist: numpy<3,>=2
Requires-Dist: pandas-stubs<3,>=2
Requires-Dist: pandas<3,>=2
Requires-Dist: poppy<2,>=1
Requires-Dist: scipy<2,>=1
Requires-Dist: tqdm<5,>=4
Requires-Dist: typing-extensions<5,>=4
Requires-Dist: xarray<2026,>=2024
